pytest_translations/__init__.py
pytest_translations/config.py
pytest_translations/mo_files.py
pytest_translations/po_files.py
pytest_translations/po_spelling.py
pytest_translations/utils.py
pytest_translations-5.0.0.dist-info/LICENSE
pytest_translations-5.0.0.dist-info/METADATA
pytest_translations-5.0.0.dist-info/WHEEL
pytest_translations-5.0.0.dist-info/entry_points.txt
pytest_translations-5.0.0.dist-info/RECORD
