Metadata-Version: 2.1
Name: pytest-translations
Version: 5.0.0
Summary: Test your translation files.
Home-page: https://github.com/Thermondo/pytest-translations
License: Apache-2.0
Author: thermondo
Author-email: opensource@thermondo.de
Requires-Python: >=3.8,<4.0
Classifier: Development Status :: 5 - Production/Stable
Classifier: Environment :: Web Environment
Classifier: Intended Audience :: Developers
Classifier: License :: OSI Approved :: Apache Software License
Classifier: Natural Language :: English
Classifier: Operating System :: OS Independent
Classifier: Programming Language :: Python :: 3
Classifier: Programming Language :: Python :: 3.8
Classifier: Programming Language :: Python :: 3.9
Classifier: Programming Language :: Python :: 3.10
Classifier: Programming Language :: Python :: 3.11
Requires-Dist: polib (>=1.0.5)
Requires-Dist: pyenchant (>=1.6.0)
Requires-Dist: pytest (>=7)
Project-URL: Repository, https://github.com/Thermondo/pytest-translations
